CHANGELOG.rst
README.rst
quacks/__init__.py
quacks/mypy.py
quacks/py.typed
quacks-1.1.1.dist-info/LICENSE
quacks-1.1.1.dist-info/METADATA
quacks-1.1.1.dist-info/WHEEL
quacks-1.1.1.dist-info/RECORD
