Metadata-Version: 2.1
Name: quacks
Version: 1.1.1
Summary: Better duck-typing with mypy-compatible extensions to Protocol
Home-page: https://github.com/ariebovenberg/quacks
License: MIT
Keywords: ducktyping,protocol,mypy,immutability
Author: Arie Bovenberg
Author-email: a.c.bovenberg@gmail.com
Requires-Python: >=3.8.1,<4.0.0
Classifier: License :: OSI Approved :: MIT License
Classifier: Programming Language :: Python :: 3
Classifier: Programming Language :: Python :: 3.9
Classifier: Programming Language :: Python :: 3.10
Classifier: Programming Language :: Python :: 3.11
Classifier: Programming Language :: Python :: 3.12
Classifier: Programming Language :: Python :: 3.13
Classifier: Topic :: Software Development :: Libraries :: Python Modules
Classifier: Typing :: Typed
Project-URL: Repository, https://github.com/ariebovenberg/quacks
